patronus/__init__.py
patronus/authentication.py
patronus/cache.py
patronus/context.py
patronus/decorators.py
patronus/exceptions.py
patronus/middleware.py
patronus/permissions.py
patronus/profile_loader.py
patronus/settings.py
patronus/user.py
patronus/providers/__init__.py
patronus/providers/base.py
patronus/providers/gcip.py
novah_patronus-0.2.0.dist-info/METADATA
novah_patronus-0.2.0.dist-info/WHEEL
novah_patronus-0.2.0.dist-info/RECORD
