Metadata-Version: 2.4
Name: novah-patronus
Version: 0.2.0
Summary: Production-ready, provider-agnostic authentication library for Django REST Framework applications in the Novah Care ecosystem
Project-URL: Homepage, https://github.com/novahcare/patronus
Project-URL: Documentation, https://github.com/novahcare/patronus#readme
Project-URL: Repository, https://github.com/novahcare/patronus.git
Project-URL: Issues, https://github.com/novahcare/patronus/issues
Author-email: Novah Care <engineering@novahcare.com>
License-Expression: MIT
Keywords: api,authentication,authorization,django,drf,firebase,gcip,rest
Classifier: Development Status :: 3 - Alpha
Classifier: Framework :: Django
Classifier: Framework :: Django :: 6.0
Classifier: Intended Audience :: Developers
Classifier: License :: OSI Approved :: MIT License
Classifier: Operating System :: OS Independent
Classifier: Programming Language :: Python :: 3
Classifier: Programming Language :: Python :: 3.13
Classifier: Topic :: Security
Classifier: Topic :: Software Development :: Libraries :: Python Modules
Requires-Python: >=3.13
Requires-Dist: django>=6.0
Requires-Dist: djangorestframework>=3.14
Requires-Dist: firebase-admin>=6.0
Provides-Extra: dev
Requires-Dist: build>=1.0; extra == 'dev'
Requires-Dist: django-stubs>=4.0; extra == 'dev'
Requires-Dist: djangorestframework-stubs>=3.14; extra == 'dev'
Requires-Dist: mypy>=1.0; extra == 'dev'
Requires-Dist: pre-commit>=3.0; extra == 'dev'
Requires-Dist: pytest-asyncio>=0.23; extra == 'dev'
Requires-Dist: pytest-cov>=4.0; extra == 'dev'
Requires-Dist: pytest-django>=4.5; extra == 'dev'
Requires-Dist: pytest>=8.0; extra == 'dev'
Requires-Dist: ruff>=0.1; extra == 'dev'
Requires-Dist: twine>=5.0; extra == 'dev'
